{
  "employee": [
    {
      "id": "4",
      "name": "Nahid Pawaskar",
      "department": "Testing",
      "age": "29",
      "gender": "Female",
      "salary": "14555",
      "yearsOfExperience": "35"
    },
    {
      "id": "5",
      "name": "Sruthi Narayan",
      "department": "Manager",
      "age": "22",
      "gender": "Female",
      "salary": "2500",
      "yearsOfExperience": "2"
    },
    {
      "id": "4",
      "name": "Massita",
      "department": "Development",
      "age": "25",
      "gender": "Female",
      "salary": "4500",
      "yearsOfExperience": "3"
    }
  ]
}